{
  "appPageId" : "e4bd7437-87f9-492f-bb9b-cca60c9128dd",
  "componentName" : "siteforce:sldsOneColLayout",
  "dataProviders" : [ ],
  "id" : "7625b2c8-7bd7-4333-b33d-e910bbc2d50c",
  "label" : "Dashboard Detail",
  "regions" : [ {
    "id" : "6ea3cdaf-290f-4182-9417-12a6f9e08e70",
    "regionName" : "header",
    "type" : "region"
  }, {
    "components" : [ {
      "componentAttributes" : {
        "height" : "1065",
        "recordId" : "{!recordId}"
      },
      "componentName" : "forceCommunity:dashboard",
      "id" : "de8e596d-f410-41e4-ab4d-30c137f04b0c",
      "renderPriority" : "NEUTRAL",
      "renditionMap" : { },
      "type" : "component"
    } ],
    "id" : "ee3a9b13-6ca0-4c9d-a247-22621963cb1f",
    "regionName" : "content",
    "type" : "region"
  }, {
    "components" : [ {
      "componentAttributes" : {
        "askCommunityLabel" : "Ask A Question",
        "contactSupportLabel" : "Contact Support",
        "headerLabel" : "Don't see what you're looking for?"
      },
      "componentName" : "siteforce:napiliFooter",
      "id" : "0270dd46-983e-434a-b874-30031c352c5f",
      "renderPriority" : "NEUTRAL",
      "renditionMap" : { },
      "type" : "component"
    } ],
    "id" : "bbf10919-c4dd-42b4-8be8-819da6ec607f",
    "regionName" : "footer",
    "type" : "region"
  }, {
    "components" : [ {
      "componentAttributes" : {
        "customHeadTags" : "",
        "description" : "",
        "title" : "{!Record._Object}: {!Record._Title}"
      },
      "componentName" : "forceCommunity:seoAssistant",
      "id" : "f8cae8f2-57f1-4a0c-81d8-e36df25635a2",
      "renditionMap" : { },
      "type" : "component"
    } ],
    "id" : "90c51b36-307d-4c28-b27d-3458df69bd35",
    "regionName" : "sfdcHiddenRegion",
    "type" : "region"
  } ],
  "themeLayoutType" : "Inner",
  "type" : "view",
  "viewType" : "detail-01Z"
}