{
  "appPageId" : "e4bd7437-87f9-492f-bb9b-cca60c9128dd",
  "componentName" : "siteforce:dynamicLayout",
  "dataProviders" : [ ],
  "id" : "4e93c47e-da0d-4a39-8b27-e7e2c945ffaf",
  "label" : "Enablement Program Milestone",
  "regions" : [ {
    "id" : "503780c5-9495-4807-ad61-3dd5da8e1a22",
    "regionName" : "header",
    "type" : "region"
  }, {
    "components" : [ {
      "componentAttributes" : {
        "background" : "background: rgba(0,0,0,0)",
        "backgroundOverlay" : "rgba(0,0,0,0.5)",
        "contentAreaWidth" : 100,
        "sectionConfig" : {
          "UUID" : "8f59ceb0-ddc4-4d2d-906e-d5818dc50f4e",
          "columns" : [ {
            "UUID" : "aeb4184c-c1b6-4a1d-938d-109c57edb29a",
            "columnKey" : "col1",
            "columnName" : "column 1",
            "columnWidth" : "12",
            "seedComponents" : [ {
              "attributes" : {
                "sfdc:identifier" : "runtime_ses_ext_contentDetailHeader"
              },
              "fqn" : "runtime_ses_ext:contentDetailHeader"
            } ]
          } ]
        },
        "sectionHeight" : 32
      },
      "componentName" : "forceCommunity:section",
      "id" : "8f59ceb0-ddc4-4d2d-906e-d5818dc50f4e",
      "regions" : [ {
        "components" : [ {
          "componentAttributes" : {
            "recordId" : "{!recordId}",
            "showDueDate" : true,
            "titleHeadingLevel" : "h1"
          },
          "componentName" : "runtime_ses_ext:contentDetailHeader",
          "id" : "706915e3-15a7-41b0-8a5e-5ed6c17d248c",
          "renderPriority" : "NEUTRAL",
          "renditionMap" : { },
          "type" : "component"
        } ],
        "id" : "aeb4184c-c1b6-4a1d-938d-109c57edb29a",
        "regionLabel" : "column 1",
        "regionName" : "col1",
        "renditionMap" : { },
        "type" : "region"
      } ],
      "renderPriority" : "NEUTRAL",
      "renditionMap" : { },
      "type" : "component"
    }, {
      "componentAttributes" : {
        "background" : "background: rgba(0,0,0,0)",
        "backgroundOverlay" : "rgba(0,0,0,0.5)",
        "contentAreaWidth" : 100,
        "sectionConfig" : {
          "UUID" : "0bd06274-6b70-4834-abd6-523983a612ee",
          "columns" : [ {
            "UUID" : "1ec66a64-c15d-4c34-bb07-e707dae2a3a4",
            "columnKey" : "col1",
            "columnName" : "column 1",
            "columnWidth" : "8",
            "seedComponents" : [ {
              "attributes" : {
                "richTextValue" : "<hr class=\"slds-m-top_none\"/>",
                "sfdc:identifier" : "forceCommunity_htmlBlock"
              },
              "fqn" : "forceCommunity:htmlBlock"
            }, {
              "attributes" : {
                "sfdc:identifier" : "runtime_ses_ext_milestoneDetail"
              },
              "fqn" : "runtime_ses_ext:milestoneDetail"
            }, {
              "attributes" : {
                "richTextValue" : "<hr/>",
                "sfdc:identifier" : "forceCommunity_htmlBlock"
              },
              "fqn" : "forceCommunity:htmlBlock"
            } ]
          }, {
            "UUID" : "a278ec5a-e327-42b3-8037-3699a17c5943",
            "columnKey" : "col2",
            "columnName" : "column 2",
            "columnWidth" : "4",
            "seedComponents" : [ {
              "attributes" : {
                "displayAsCard" : "true",
                "displayMode" : "compact",
                "sfdc:identifier" : "runtime_ses_ext_programDetailHeader",
                "showDescription" : "false"
              },
              "fqn" : "runtime_ses_ext:programDetailHeader"
            }, {
              "attributes" : {
                "displayAsCard" : "true",
                "sfdc:identifier" : "runtime_ses_ext_programOutcomeCard",
                "showDescription" : "false",
                "showIcon" : "false",
                "title" : ""
              },
              "fqn" : "runtime_ses_ext:programOutcomeCard"
            }, {
              "attributes" : {
                "sfdc:identifier" : "runtime_ses_ext_programTaskListCard"
              },
              "fqn" : "runtime_ses_ext:programTaskListCard"
            } ]
          } ]
        },
        "sectionHeight" : 32
      },
      "componentName" : "forceCommunity:section",
      "id" : "0bd06274-6b70-4834-abd6-523983a612ee",
      "regions" : [ {
        "components" : [ {
          "componentAttributes" : {
            "richTextValue" : "<hr class=\"slds-m-top_none\"/>"
          },
          "componentName" : "forceCommunity:htmlBlock",
          "id" : "e8fe3801-06eb-4e54-a9a4-3231a391b8af",
          "renderPriority" : "NEUTRAL",
          "renditionMap" : { },
          "type" : "component"
        }, {
          "componentAttributes" : {
            "recordId" : "{!recordId}"
          },
          "componentName" : "runtime_ses_ext:milestoneDetail",
          "id" : "f8749309-fbac-4caa-8a19-ad7e22afed82",
          "renderPriority" : "NEUTRAL",
          "renditionMap" : { },
          "type" : "component"
        }, {
          "componentAttributes" : {
            "richTextValue" : "<hr/>"
          },
          "componentName" : "forceCommunity:htmlBlock",
          "id" : "c5e476d7-76f0-4ef1-a711-60724334bb81",
          "renderPriority" : "NEUTRAL",
          "renditionMap" : { },
          "type" : "component"
        } ],
        "id" : "1ec66a64-c15d-4c34-bb07-e707dae2a3a4",
        "regionLabel" : "column 1",
        "regionName" : "col1",
        "renditionMap" : { },
        "type" : "region"
      }, {
        "components" : [ {
          "componentAttributes" : {
            "displayAsCard" : true,
            "displayMode" : "compact",
            "recordId" : "{!recordId}",
            "showDescription" : false,
            "showDueDate" : true,
            "titleHeadingLevel" : "h1"
          },
          "componentName" : "runtime_ses_ext:programDetailHeader",
          "id" : "310b6924-af41-498a-888a-918a1a420f93",
          "renderPriority" : "NEUTRAL",
          "renditionMap" : { },
          "type" : "component"
        }, {
          "componentAttributes" : {
            "displayAsCard" : true,
            "recordId" : "{!recordId}",
            "showDescription" : false,
            "showDueDate" : true,
            "showIcon" : false,
            "title" : "",
            "titleHeadingLevel" : "h2",
            "titleStyle" : "small"
          },
          "componentName" : "runtime_ses_ext:programOutcomeCard",
          "id" : "49a65136-9aa2-4e06-a885-08c013f5f16f",
          "renderPriority" : "NEUTRAL",
          "renditionMap" : { },
          "type" : "component"
        }, {
          "componentAttributes" : {
            "displayAsCard" : true,
            "recordId" : "{!recordId}",
            "showDescription" : true,
            "showDueDate" : true,
            "showExpandOrCollapseButtons" : true,
            "showIcons" : true,
            "showProgress" : true,
            "title" : "Milestones and Tasks",
            "titleHeadingLevel" : "h2",
            "titleStyle" : "small"
          },
          "componentName" : "runtime_ses_ext:programTaskListCard",
          "id" : "424e0730-c999-4e78-8548-bc5d1df68197",
          "renderPriority" : "NEUTRAL",
          "renditionMap" : { },
          "type" : "component"
        } ],
        "id" : "a278ec5a-e327-42b3-8037-3699a17c5943",
        "regionLabel" : "column 2",
        "regionName" : "col2",
        "renditionMap" : { },
        "type" : "region"
      } ],
      "renderPriority" : "NEUTRAL",
      "renditionMap" : { },
      "type" : "component"
    } ],
    "id" : "f80e3002-9f42-44b4-8e59-3d360ab2a0a0",
    "regionName" : "content",
    "type" : "region"
  }, {
    "id" : "7e83449e-c470-446e-8872-49ec772e5c02",
    "regionName" : "footer",
    "type" : "region"
  } ],
  "themeLayoutType" : "Inner",
  "type" : "view",
  "viewType" : "enablement-program-milestone"
}