{
  "appPageId" : "4f64a16a-eb7f-4c9c-b56a-5fb19dc79e19",
  "componentName" : "siteforce:dynamicLayout",
  "dataProviders" : [ ],
  "id" : "97102b3a-582c-4ff9-93a9-383ab95d16e5",
  "label" : "Enablement Program Link",
  "regions" : [ {
    "id" : "0b638981-4e68-4f0f-9eb0-2b0ed88454c0",
    "regionName" : "header",
    "type" : "region"
  }, {
    "components" : [ {
      "componentAttributes" : {
        "background" : "background: rgba(0,0,0,0)",
        "backgroundOverlay" : "rgba(0,0,0,0.5)",
        "contentAreaWidth" : 100,
        "sectionConfig" : {
          "UUID" : "b2eeca9c-5d76-43e2-a872-3669b1bba90a",
          "columns" : [ {
            "UUID" : "8b44fd40-83eb-4ba0-b6a4-8e36d8495e55",
            "columnKey" : "col1",
            "columnName" : "column 1",
            "columnWidth" : "12",
            "seedComponents" : [ {
              "attributes" : {
                "sfdc:identifier" : "runtime_ses_ext_contentDetailHeader"
              },
              "fqn" : "runtime_ses_ext:contentDetailHeader"
            } ]
          } ]
        },
        "sectionHeight" : 32
      },
      "componentName" : "forceCommunity:section",
      "id" : "b2eeca9c-5d76-43e2-a872-3669b1bba90a",
      "regions" : [ {
        "components" : [ {
          "componentAttributes" : {
            "recordId" : "{!recordId}",
            "showDueDate" : true,
            "titleHeadingLevel" : "h1"
          },
          "componentName" : "runtime_ses_ext:contentDetailHeader",
          "id" : "8771a789-2a1a-462a-8b57-87dc8ba9151e",
          "renderPriority" : "NEUTRAL",
          "renditionMap" : { },
          "type" : "component"
        } ],
        "id" : "8b44fd40-83eb-4ba0-b6a4-8e36d8495e55",
        "regionLabel" : "column 1",
        "regionName" : "col1",
        "renditionMap" : { },
        "type" : "region"
      } ],
      "renderPriority" : "NEUTRAL",
      "renditionMap" : { },
      "type" : "component"
    }, {
      "componentAttributes" : {
        "background" : "background: rgba(0,0,0,0)",
        "backgroundOverlay" : "rgba(0,0,0,0.5)",
        "contentAreaWidth" : 100,
        "sectionConfig" : {
          "UUID" : "4aa9e0dc-8f24-4667-a4f1-e21140d403ae",
          "columns" : [ {
            "UUID" : "48ac25fe-5b0b-4229-bb45-fc41d1decc66",
            "columnKey" : "col1",
            "columnName" : "column 1",
            "columnWidth" : "8",
            "seedComponents" : [ {
              "attributes" : {
                "sfdc:identifier" : "runtime_ses_ext_linkDetail"
              },
              "fqn" : "runtime_ses_ext:linkDetail"
            } ]
          }, {
            "UUID" : "c4fedb56-647d-4e46-bbac-b99be2875412",
            "columnKey" : "col2",
            "columnName" : "column 2",
            "columnWidth" : "4",
            "seedComponents" : [ {
              "attributes" : {
                "displayAsCard" : "true",
                "displayMode" : "compact",
                "sfdc:identifier" : "runtime_ses_ext_programDetailHeader",
                "showDescription" : "false"
              },
              "fqn" : "runtime_ses_ext:programDetailHeader"
            }, {
              "attributes" : {
                "sfdc:identifier" : "runtime_ses_ext_programTaskListCard",
                "showIcons" : "false"
              },
              "fqn" : "runtime_ses_ext:programTaskListCard"
            } ]
          } ]
        },
        "sectionHeight" : 32
      },
      "componentName" : "forceCommunity:section",
      "id" : "4aa9e0dc-8f24-4667-a4f1-e21140d403ae",
      "regions" : [ {
        "components" : [ {
          "componentAttributes" : {
            "recordId" : "{!recordId}"
          },
          "componentName" : "runtime_ses_ext:linkDetail",
          "id" : "ea6ede8e-e390-4321-a851-b2ab93c7c325",
          "renderPriority" : "NEUTRAL",
          "renditionMap" : { },
          "type" : "component"
        } ],
        "id" : "48ac25fe-5b0b-4229-bb45-fc41d1decc66",
        "regionLabel" : "column 1",
        "regionName" : "col1",
        "renditionMap" : { },
        "type" : "region"
      }, {
        "components" : [ {
          "componentAttributes" : {
            "displayAsCard" : true,
            "displayMode" : "compact",
            "recordId" : "{!recordId}",
            "showDescription" : false,
            "showDueDate" : true,
            "titleHeadingLevel" : "h1"
          },
          "componentName" : "runtime_ses_ext:programDetailHeader",
          "id" : "858d37b5-7fcd-48f1-a29d-f363bdaa2c2f",
          "renderPriority" : "NEUTRAL",
          "renditionMap" : { },
          "type" : "component"
        }, {
          "componentAttributes" : {
            "displayAsCard" : true,
            "recordId" : "{!recordId}",
            "showDescription" : true,
            "showDueDate" : true,
            "showExpandOrCollapseButtons" : true,
            "showIcons" : false,
            "showProgress" : true,
            "title" : "Milestones and Tasks",
            "titleHeadingLevel" : "h2",
            "titleStyle" : "small"
          },
          "componentName" : "runtime_ses_ext:programTaskListCard",
          "id" : "e4ff2d42-0dc1-465d-bd9c-f6630bd4240d",
          "renderPriority" : "NEUTRAL",
          "renditionMap" : { },
          "type" : "component"
        } ],
        "id" : "c4fedb56-647d-4e46-bbac-b99be2875412",
        "regionLabel" : "column 2",
        "regionName" : "col2",
        "renditionMap" : { },
        "type" : "region"
      } ],
      "renderPriority" : "NEUTRAL",
      "renditionMap" : { },
      "type" : "component"
    } ],
    "id" : "1a5db7cb-505f-456c-a09f-02e393982d8a",
    "regionName" : "content",
    "type" : "region"
  }, {
    "id" : "a9f9dfff-d071-428f-b706-746e6d168922",
    "regionName" : "footer",
    "type" : "region"
  } ],
  "themeLayoutType" : "Inner",
  "type" : "view",
  "viewType" : "enablement-program-link"
}